pymodaq_plugins_newport/__init__.py
pymodaq_plugins_newport/utils.py
pymodaq_plugins_newport/daq_move_plugins/__init__.py
pymodaq_plugins_newport/daq_move_plugins/daq_move_Conex.py
pymodaq_plugins_newport/daq_move_plugins/daq_move_Newport_AgilisSerial.py
pymodaq_plugins_newport/daq_move_plugins/daq_move_Newport_ESP100.py
pymodaq_plugins_newport/daq_move_plugins/daq_move_Newport_Picomotor8742.py
pymodaq_plugins_newport/daq_move_plugins/daq_move_Newport_SMC100.py
pymodaq_plugins_newport/daq_move_plugins/daq_move_XpsQ8.py
pymodaq_plugins_newport/daq_viewer_plugins/__init__.py
pymodaq_plugins_newport/daq_viewer_plugins/plugins_0D/__init__.py
pymodaq_plugins_newport/daq_viewer_plugins/plugins_1D/__init__.py
pymodaq_plugins_newport/daq_viewer_plugins/plugins_2D/__init__.py
pymodaq_plugins_newport/hardware/XPS_Q8_drivers.py
pymodaq_plugins_newport/hardware/__init__.py
pymodaq_plugins_newport/hardware/agilis_serial.py
pymodaq_plugins_newport/hardware/esp100.py
pymodaq_plugins_newport/hardware/serial_base.py
pymodaq_plugins_newport/hardware/smc100.py
pymodaq_plugins_newport/hardware/xps_q8_simplified.py
pymodaq_plugins_newport/resources/__init__.py
pymodaq_plugins_newport/resources/config_template.toml
pymodaq_plugins_newport-5.0.0.dist-info/METADATA
pymodaq_plugins_newport-5.0.0.dist-info/WHEEL
pymodaq_plugins_newport-5.0.0.dist-info/entry_points.txt
pymodaq_plugins_newport-5.0.0.dist-info/licenses/LICENSE
pymodaq_plugins_newport-5.0.0.dist-info/RECORD
