Metadata-Version: 2.4
Name: pymodaq_plugins_newport
Version: 5.0.0
Summary: Set of PyMoDAQ plugins for instruments from Newport (Conex, ESP100, SMC100, AG-CU8, ...)
Project-URL: Homepage, https://pymodaq.cnrs.fr
Project-URL: Documentation , https://pymodaq.cnrs.fr
Project-URL: Repository , https://github.com/PyMoDAQ/pymodaq_plugins_newport
Author-email: "Weber J. Sebastien" <sebastien.weber@cnrs.fr>
Maintainer-email: "Weber J. Sebastien" <sebastien.weber@cnrs.fr>
License: The MIT License (MIT)
License-File: LICENSE
Classifier: Development Status :: 5 - Production/Stable
Classifier: Intended Audience :: Science/Research
Classifier: License :: OSI Approved :: MIT License
Classifier: Natural Language :: English
Classifier: Operating System :: OS Independent
Classifier: Programming Language :: Python :: 3.8
Classifier: Programming Language :: Python :: 3.9
Classifier: Programming Language :: Python :: 3.10
Classifier: Programming Language :: Python :: 3.11
Classifier: Topic :: Scientific/Engineering :: Human Machine Interfaces
Classifier: Topic :: Scientific/Engineering :: Visualization
Classifier: Topic :: Software Development :: Libraries :: Python Modules
Classifier: Topic :: Software Development :: User Interfaces
Requires-Python: >=3.8
Requires-Dist: pylablib
Requires-Dist: pymodaq>=5.0.0
Requires-Dist: pythonnet
Requires-Dist: pyvisa
Requires-Dist: pyvisa-py
